pywps/__init__.py
pywps/_compat.py
pywps/configuration.py
pywps/dblog.py
pywps/dependencies.py
pywps/exceptions.py
pywps/ext_autodoc.py
pywps/tests.py
pywps/wpsserver.py
pywps/app/Common.py
pywps/app/Process.py
pywps/app/Service.py
pywps/app/WPSRequest.py
pywps/app/__init__.py
pywps/app/basic.py
pywps/inout/__init__.py
pywps/inout/basic.py
pywps/inout/inputs.py
pywps/inout/literaltypes.py
pywps/inout/outputs.py
pywps/inout/storage.py
pywps/inout/formats/__init__.py
pywps/processing/__init__.py
pywps/processing/basic.py
pywps/processing/job.py
pywps/processing/scheduler.py
pywps/resources/__init__.py
pywps/resources/schemas/__init__.py
pywps/resources/schemas/wps_all.xsd
pywps/response/__init__.py
pywps/response/capabilities.py
pywps/response/describe.py
pywps/response/execute.py
pywps/response/status.py
pywps/schemas/geojson/README
pywps/schemas/geojson/bbox.json
pywps/schemas/geojson/crs.json
pywps/schemas/geojson/geojson.json
pywps/schemas/geojson/geometry.json
pywps/templates/1.0.0/capabilities/main.xml
pywps/templates/1.0.0/describe/bbox.xml
pywps/templates/1.0.0/describe/complex.xml
pywps/templates/1.0.0/describe/literal.xml
pywps/templates/1.0.0/describe/main.xml
pywps/templates/1.0.0/execute/main.xml
pywps/templates/2.0.0/capabilities/main.xml
pywps/validator/__init__.py
pywps/validator/allowed_value.py
pywps/validator/base.py
pywps/validator/complexvalidator.py
pywps/validator/literalvalidator.py
pywps/validator/mode.py
pywps-4.2.1.dist-info/LICENSE.txt
pywps-4.2.1.dist-info/METADATA
pywps-4.2.1.dist-info/WHEEL
pywps-4.2.1.dist-info/entry_points.txt
pywps-4.2.1.dist-info/top_level.txt
pywps-4.2.1.dist-info/RECORD
