Metadata-Version: 2.1
Name: pywps
Version: 4.2.1
Summary: PyWPS is an implementation of the Web Processing Service standard from the Open Geospatial Consortium. PyWPS is written in Python.
Home-page: http://pywps.org
Author: Jachym Cepicky
Author-email: jachym.cepicky@gmail.com
License: MIT
Download-URL: https://github.com/geopython/pywps
Keywords: PyWPS WPS OGC processing
Platform: all
Classifier: Development Status :: 5 - Production/Stable
Classifier: Environment :: Web Environment
Classifier: Intended Audience :: Developers
Classifier: Intended Audience :: Science/Research
Classifier: License :: OSI Approved :: MIT License
Classifier: Operating System :: OS Independent
Classifier: Programming Language :: Python
Classifier: Topic :: Scientific/Engineering :: GIS
Requires-Dist: flufl.enum
Requires-Dist: jinja2
Requires-Dist: jsonschema
Requires-Dist: lxml
Requires-Dist: owslib
Requires-Dist: pathlib
Requires-Dist: python-dateutil
Requires-Dist: requests
Requires-Dist: SQLAlchemy
Requires-Dist: werkzeug
